<?xml version="1.0" encoding="UTF-8" standalone="yes"?>
<addon id="service.subtitles.acfun"
       name="Acfun 弹幕"
       version="0.1.1"
       provider-name="xodidox,zhengfan,shaolin-kongfu">
    <requires>
        <import addon="xbmc.python" version="2.1.0"/>
        <import addon="script.module.requests" version="1.1.0"/>
        <import addon="script.module.beautifulsoup4" version="4.3.2"/>
        <import addon="vfs.rar" version="2.3.0"/>
    </requires>
    <extension point="xbmc.subtitle.module"
               library="service.py" />
    <extension point="xbmc.addon.metadata">
        <summary lang="zh">Acfun 弹幕插件</summary>
        <description lang="zh">从 Acfun 下载弹幕</description>
        <assets>
            <icon>icon.png</icon>
            <clearlogo>logo.png</clearlogo>
            <fanart>resources/media/fanart.jpg</fanart>
            <screenshot>resources/media/screenshot_1.png</screenshot>
            <screenshot>resources/media/screenshot_2.png</screenshot>
            <screenshot>resources/media/screenshot_3.png</screenshot>
        </assets>
        <news></news>
    </extension>
</addon>
<addon id="service.subtitles.bilibili"
       name="Bilibili 弹幕"
       version="0.1.1"
       provider-name="xodidox,zhengfan,shaolin-kongfu">
    <requires>
        <import addon="xbmc.python" version="2.1.0"/>
        <import addon="script.module.requests" version="1.1.0"/>
        <import addon="script.module.beautifulsoup4" version="4.3.2"/>
        <import addon="vfs.rar" version="2.3.0"/>
    </requires>
    <extension point="xbmc.subtitle.module"
               library="service.py" />
    <extension point="xbmc.addon.metadata">
        <summary lang="zh">哔哩哔哩 弹幕插件</summary>
        <description lang="zh">从 哔哩哔哩 下载弹幕</description>
        <assets>
            <icon>icon.png</icon>
            <clearlogo>logo.png</clearlogo>
            <fanart>resources/media/fanart.jpg</fanart>
            <screenshot>resources/media/screenshot_1.png</screenshot>
            <screenshot>resources/media/screenshot_2.png</screenshot>
            <screenshot>resources/media/screenshot_3.png</screenshot>
        </assets>
        <news></news>
    </extension>
</addon>
<addon id="repository.xbmc-kodi-private-china-addons"
        name="Chinese Add-ons"
        version="1.0.0"
        provider-name="zhengfan2014">
    <extension point="xbmc.addon.repository"
            name="Chinese Add-ons">
        <info compressed="true">https://github.com/FadeJay/xbmc-kodi-private-china-addons/raw/py3/addons.xml</info>
        <checksum>https://github.com/FadeJay/xbmc-kodi-private-china-addons/raw/py3/addons.xml.md5</checksum>
        <datadir zip="true">https://github.com/FadeJay/xbmc-kodi-private-china-addons/raw/py3/repo</datadir>
    </extension>
    <extension point="xbmc.addon.metadata">
        <summary>Chinese Add-ons Repository</summary>
        <summary lang="zh">面向中文用户的插件库</summary>
        <description>xbmc-kodi-private-china-addons is a GitHub repository for Kodi add-ons written and maintained by zhengfan2014. Kodi can be added to play video sites such as Bilibili and mount barrage and other weird functions.</description>
        <description lang="zh">xbmc-kodi-private-china-addons 是一个存放由zhengfan2014编写和维护的Kodi插件的GitHub仓库。可以为Kodi增加播放Bilibili等视频网站和挂载弹幕等奇奇怪怪的功能。</description>
        <disclaimer>I am not responsible for the content provided by the plug-in</disclaimer>
        <disclaimer lang="zh">本人对插件提供的内容不承担责任</disclaimer>
        <platform>all</platform>
        <assets>
            <icon>icon.png</icon>
        </assets>
    </extension>
</addon>
</addons>
